[
  {
    "title": "Robot salvaje",
    "link": "https://cinetux.top/pelicula/robot-salvaje/",
    "image": "https://cinetux.top/wp-content/themes/toroflix%202/public/img/cnt/noimga.svg",
    "year": "2024",
    "quality": "1080 HD",
    "duration": "1h 42m",
    "description": "El épico viaje de un robot -la unidad 7134 de Roz,'Roz' para abreviar- que naufraga",
    "director": "Chris Sanders",
    "genres": [
      "Animación",
      "Ciencia ficción",
      "Familia"
    ],
    "actors": [
      "Alessandro Beghi",
      "Alexandra Novelle",
      "Avrielle Corti",
      "Becca Last",
      "Beckett Blomberg",
      "Bill Nighy",
      "Boone Storm",
      "Catherine O'Hara",
      "Collin Erker",
      "Damon Fung",
      "Dee Bradley Baker",
      "Eddie Park"
    ]
  },
  {
    "title": "La mujer del momento",
    "link": "https://cinetux.top/pelicula/la-mujer-del-momento/",
    "image": "https://cinetux.top/wp-content/themes/toroflix%202/public/img/cnt/noimga.svg",
    "year": "2024",
    "quality": "1080 HD",
    "duration": "1h 34m",
    "description": "Las vidas de una aspirante a actriz y un prolífico asesino en serie se cruzan",
    "director": "Anna Kendrick",
    "genres": [
      "Crimen",
      "Drama",
      "Suspense"
    ],
    "actors": [
      "Andy Thompson",
      "Anna Kendrick",
      "Autumn Best",
      "Bonnie Hay",
      "Daniel Zovatto",
      "Darcy Laurie",
      "David Beairsto",
      "Denalda Williams",
      "Dylan Schmid",
      "Geoff Gustafson",
      "Hannah Henney",
      "Jacob Woike"
    ]
  },
  {
    "title": "Smile 2",
    "link": "https://cinetux.top/pelicula/smile-2/",
    "image": "https://cinetux.top/wp-content/themes/toroflix%202/public/img/cnt/noimga.svg",
    "year": "2024",
    "quality": "TS-Screener",
    "duration": "2h 7m",
    "description": "La estrella del pop mundial Skye Riley está a punto de embarcarse en una nueva",
    "director": "Anthony Pettine",
    "genres": [
      "Misterio",
      "Terror"
    ],
    "actors": [
      "Charlie Sarroff",
      "Daphne Zelle",
      "Delphi Harrington",
      "Drew Barrymore",
      "Dylan Gelula",
      "Erika Chase",
      "Ivan Carlo",
      "Jon Rua",
      "Jon Seeber",
      "Kyle Gallner",
      "Lukas Gage",
      "Mila Falkof"
    ]
  },
  {
    "title": "La Sustancia",
    "link": "https://cinetux.top/pelicula/la-sustancia/",
    "image": "https://cinetux.top/wp-content/themes/toroflix%202/public/img/cnt/noimga.svg",
    "year": "2024",
    "quality": "1080 HD",
    "duration": "2h 21m",
    "description": "\"Tú, pero mejor en todos los sentidos\". Esa es la promesa de La Sustancia, un",
    "director": "Anne Juin",
    "genres": [
      "Ciencia ficción",
      "Drama",
      "Terror"
    ],
    "actors": [
      "Aaron Kahn",
      "Adam Carage",
      "Akil Wingate",
      "Andrew Desmond",
      "Andrew Eldridge",
      "Arthur Molinet",
      "Ashley Lambert",
      "Aurélien Lorgnier",
      "Axel Baille",
      "Barthelemy Thomas",
      "Bastien Jorelle",
      "Benoit Lévêque"
    ]
  },
  {
    "title": "Lee",
    "link": "https://cinetux.top/pelicula/lee/",
    "image": "https://cinetux.top/wp-content/themes/toroflix%202/public/img/cnt/noimga.svg",
    "year": "2024",
    "quality": "TS-Screener",
    "duration": "1h 57m",
    "description": "La historia de la fotógrafa Elizabeth 'Lee' Miller, una modelo que se convirtió en una",
    "director": "Ellen Kuras",
    "genres": [
      "Bélica",
      "Drama",
      "Historia"
    ],
    "actors": [
      "Alexander Skarsgård",
      "Andrea Riseborough",
      "Andy Samberg",
      "Arinzé Kene",
      "Enrique Arce",
      "Harriet Leitch",
      "Ian Dunnett Jnr",
      "James Murray",
      "Josh O'Connor",
      "Katalin Ruzsik",
      "Kate Winslet",
      "Marion Cotillard"
    ]
  },
  {
    "title": "Bagman. El hombre del saco",
    "link": "https://cinetux.top/pelicula/bagman-el-hombre-del-saco/",
    "image": "https://cinetux.top/wp-content/themes/toroflix%202/public/img/cnt/noimga.svg",
    "year": "2024",
    "quality": "TS-Screener",
    "duration": "1h 32m",
    "description": "Durante siglos, los padres han advertido a sus hijos sobre el temible Hombre del Saco,",
    "director": "Colm McCarthy",
    "genres": [
      "Suspense",
      "Terror"
    ],
    "actors": [
      "Adelle Leonce",
      "Antonia Thomas",
      "Frankie Corio",
      "Henry Pettigrew",
      "Neil Linpow",
      "Sam Claflin",
      "Sharon D. Clarke",
      "Steven Cree",
      "Will Davis",
      "William Hope"
    ]
  },
  {
    "title": "Terrifier 3",
    "link": "https://cinetux.top/pelicula/terrifier-3/",
    "image": "https://cinetux.top/wp-content/themes/toroflix%202/public/img/cnt/noimga.svg",
    "year": "2024",
    "quality": "TS-Screener",
    "duration": "2h 5m",
    "description": "Secuela de \"Terrifier 2\", ambientada en el periodo navideño.",
    "director": "Damien Leone",
    "genres": [
      "Suspense",
      "Terror"
    ],
    "actors": [
      "Alex Ross",
      "Alexa Blair Robertson",
      "Andrew Hollinger",
      "Annie Lederman",
      "Antonella Rose",
      "Ashton Jassar",
      "Banks Quinney",
      "Beethovan Oden",
      "Bradley Stryker",
      "Bryce Johnson",
      "Charlotte McKee",
      "Chip Carriere"
    ]
  },
  {
    "title": "Ahí afuera",
    "link": "https://cinetux.top/pelicula/ahi-afuera/",
    "image": "https://cinetux.top/wp-content/themes/toroflix%202/public/img/cnt/noimga.svg",
    "year": "2024",
    "quality": "1080 HD",
    "duration": "2h 22m",
    "description": "Durante una epidemia zombi, una familia se refugia en una granja aislada, pero sus dolorosos",
    "director": "Carlo Ledesma",
    "genres": [
      "Suspense",
      "Terror"
    ],
    "actors": [
      "Aiden Tyler Patdu",
      "Beauty Gonzalez",
      "Bing Pimentel",
      "Enchong Dee",
      "James Blanco",
      "Joel Torre",
      "Marco Antonio Masa",
      "Sid Lucero"
    ]
  },
  {
    "title": "La cueva azul",
    "link": "https://cinetux.top/pelicula/la-cueva-azul/",
    "image": "https://cinetux.top/wp-content/themes/toroflix%202/public/img/cnt/noimga.svg",
    "year": "2024",
    "quality": "1080 HD",
    "duration": "1h 28m",
    "description": "Cem, un soldado, encuentra a su media naranja cuando menos lo esperaba. Alara es una",
    "director": "Altan Dönmez",
    "genres": [
      "Drama"
    ],
    "actors": [
      "Alper Baytekin",
      "Deniz Cengiz",
      "Devrim Özkan",
      "Ece Dizdar",
      "İdil Sivritepe",
      "Kerem Bürsin",
      "Okan Yalabık",
      "Sabahattin Yakut",
      "Taner Birsel",
      "Temmuz Gürkan Karaca",
      "Yüsra Geyik"
    ]
  },
  {
    "title": "Alice",
    "link": "https://cinetux.top/pelicula/alice/",
    "image": "https://cinetux.top/wp-content/themes/toroflix%202/public/img/cnt/noimga.svg",
    "year": "2024",
    "quality": "1080 HD",
    "duration": "1h 45m",
    "description": "Un padre en apuros compra una SIM doméstica para que le ayude a cuidar de",
    "director": "SK Dale",
    "genres": [
      "Ciencia ficción",
      "Suspense",
      "Terror"
    ],
    "actors": [
      "Andrew Whipp",
      "Atanas Srebrev",
      "Doroteya Toleva",
      "Euan Macnaughton",
      "J.R. Esposito",
      "Jude Greenstein",
      "Kate Nichols",
      "Kexin Wang",
      "Madeline Zima",
      "Matilda Firth",
      "Max Kraus",
      "Megan Fox"
    ]
  },
  {
    "title": "Parpadea dos veces",
    "link": "https://cinetux.top/pelicula/parpadea-dos-veces/",
    "image": "https://cinetux.top/wp-content/themes/toroflix%202/public/img/cnt/noimga.svg",
    "year": "2024",
    "quality": "1080 HD",
    "duration": "1h 42m",
    "description": "Cuando el magnate de la tecnología Slater King (Channing Tatum) conoce a la camarera Frida",
    "director": "Zoë Kravitz",
    "genres": [
      "Misterio",
      "Suspense"
    ],
    "actors": [
      "Aaron Himelstein",
      "Adria Arjona",
      "Alia Shawkat",
      "Ben Jacobson",
      "Carlotta Kohl",
      "Caroline Forsythe",
      "Channing Tatum",
      "Christian Slater",
      "Cris Costa",
      "Eduardo Lopez Morton",
      "Emiré Arellano",
      "Garret Levitz"
    ]
  },
  {
    "title": "Diabólica",
    "link": "https://cinetux.top/pelicula/diabolica/",
    "image": "https://cinetux.top/wp-content/themes/toroflix%202/public/img/cnt/noimga.svg",
    "year": "2024",
    "quality": "1080 HD",
    "duration": "1h 24m",
    "description": "La familia de Curtis es seleccionada para probar un nuevo dispositivo para el hogar: un",
    "director": "Chris Weitz",
    "genres": [
      "Ciencia ficción",
      "Suspense",
      "Terror"
    ],
    "actors": [
      "Ashley Romans",
      "Ashton Essex Bright",
      "Ben Youcef",
      "Bennett Curran",
      "David Dastmalchian",
      "Elliott McKenzie",
      "Frank Scozzari",
      "Greg Hill",
      "Havana Rose Liu",
      "Isaac Bae",
      "Jimmy Galeota",
      "John Cho"
    ]
  },
  {
    "title": "Respira",
    "link": "https://cinetux.top/serie/respira/",
    "image": "https://cinetux.top/wp-content/themes/toroflix%202/public/img/cnt/noimga.svg",
    "year": "2024",
    "quality": "",
    "duration": "",
    "description": "Un apasionado equipo médico se entrega a salvar vidas en un hospital público desbordado, en",
    "director": "Carlos Montero",
    "genres": [
      "Drama"
    ],
    "actors": [
      "Abril Zamora",
      "Aitana Sánchez-Gijón",
      "Alfonso Bassave",
      "Ana Rayo",
      "Blanca Martínez",
      "Blanca Suárez",
      "Borja Luna",
      "Macarena de Rueda",
      "Manu Ríos",
      "Marwa Bakhat",
      "Najwa Nimri",
      "Víctor Sáinz"
    ]
  },
  {
    "title": "Tor",
    "link": "https://cinetux.top/serie/tor/",
    "image": "https://cinetux.top/wp-content/themes/toroflix%202/public/img/cnt/noimga.svg",
    "year": "2024",
    "quality": "",
    "duration": "50 min",
    "description": "La serie documental más esperada. Carles Porta revive la leyenda negra de Tor, la montaña",
    "director": "Carles Porta",
    "genres": [
      "Crimen",
      "Documental",
      "Drama"
    ],
    "actors": [
      "Carles Porta"
    ]
  },
  {
    "title": "Los héroes del tiempo",
    "link": "https://cinetux.top/serie/los-heroes-del-tiempo/",
    "image": "https://cinetux.top/wp-content/themes/toroflix%202/public/img/cnt/noimga.svg",
    "year": "2024",
    "quality": "",
    "duration": "",
    "description": "La pasión de Kevin, de once años, por la historia se verá puesta a prueba",
    "director": "Iain Morris",
    "genres": [
      "Action & Adventure",
      "Comedia",
      "Sci-Fi & Fantasy"
    ],
    "actors": [
      "Charlyne Yi",
      "Kal-El Tuck",
      "Kiera Thompson",
      "Lisa Kudrow",
      "Rachel House",
      "Roger Jean Nsengiyumva",
      "Rune Temte",
      "Tadhg Murphy"
    ]
  },
  {
    "title": "Los Detectives Muertos",
    "link": "https://cinetux.top/serie/los-detectives-muertos/",
    "image": "https://cinetux.top/wp-content/themes/toroflix%202/public/img/cnt/noimga.svg",
    "year": "2024",
    "quality": "",
    "duration": "",
    "description": "Dos fantasmas adolescentes forman equipo con una médium para resolver los misterios de su sobrenatural",
    "director": "Steve Yockey",
    "genres": [
      "Drama",
      "Misterio",
      "Sci-Fi & Fantasy"
    ],
    "actors": [
      "Briana Cuoco",
      "George Rexstrew",
      "Jayden Revri",
      "Jenn Lyon",
      "Kassius Nelson",
      "Ruth Connell",
      "Yuyu Kitamura"
    ]
  },
  {
    "title": "Mi reno de peluche",
    "link": "https://cinetux.top/serie/mi-reno-de-peluche/",
    "image": "https://cinetux.top/wp-content/themes/toroflix%202/public/img/cnt/noimga.svg",
    "year": "2024",
    "quality": "",
    "duration": "",
    "description": "Cuando un cómico en apuros tiene un gesto amable con una mujer vulnerable, desencadena una",
    "director": "Richard Gadd",
    "genres": [
      "Drama"
    ],
    "actors": [
      "Jessica Gunning",
      "Nava Mau",
      "Richard Gadd"
    ]
  },
  {
    "title": "The Continental: Del universo de John Wick",
    "link": "https://cinetux.top/serie/the-continental-del-universo-de-john-wick/",
    "image": "https://cinetux.top/wp-content/themes/toroflix%202/public/img/cnt/noimga.svg",
    "year": "2023",
    "quality": "",
    "duration": "",
    "description": "Winston Scott es arrastrado al paisaje infernal de una ciudad de Nueva York de 1975",
    "director": "Greg Coolidge",
    "genres": [
      "Action & Adventure",
      "Crimen"
    ],
    "actors": [
      "Ayomide Adegun",
      "Ben Robson",
      "Colin Woodell",
      "Hubert Point-Du Jour",
      "Jeremy Bobb",
      "Jessica Allain",
      "Mel Gibson",
      "Mishel Prada",
      "Nhung Kate",
      "Peter Greene"
    ]
  },
  {
    "title": "The Walking Dead: Daryl Dixon",
    "link": "https://cinetux.top/serie/the-walking-dead-daryl-dixon/",
    "image": "https://cinetux.top/wp-content/themes/toroflix%202/public/img/cnt/noimga.svg",
    "year": "2023",
    "quality": "",
    "duration": "",
    "description": "Meses después de que lo vimos por última vez en \"The Walking Dead\", Daryl Dixon",
    "director": "David Zabel",
    "genres": [
      "Action & Adventure",
      "Sci-Fi & Fantasy"
    ],
    "actors": [
      "Adam Nagaitis",
      "Anne Charrier",
      "Clémence Poésy",
      "Laïka Blanc-Francard",
      "Louis Puech Scigliuzzi",
      "Norman Reedus",
      "Romain Levi"
    ]
  },
  {
    "title": "Ahsoka",
    "link": "https://cinetux.top/serie/ahsoka/",
    "image": "https://cinetux.top/wp-content/themes/toroflix%202/public/img/cnt/noimga.svg",
    "year": "2023",
    "quality": "",
    "duration": "",
    "description": "Ambientada después de la caída del Imperio, la serie sigue al antiguo caballero Jedi mientras",
    "director": "Dave Filoni",
    "genres": [
      "Action & Adventure",
      "Sci-Fi & Fantasy"
    ],
    "actors": [
      "David Tennant",
      "Diana Lee Inosanto",
      "Ivanna Sakhno",
      "Mary Elizabeth Winstead",
      "Natasha Liu Bordizzo",
      "Ray Stevenson",
      "Rosario Dawson"
    ]
  },
  {
    "title": "La rueda del tiempo",
    "link": "https://cinetux.top/serie/la-rueda-del-tiempo/",
    "image": "https://cinetux.top/wp-content/themes/toroflix%202/public/img/cnt/noimga.svg",
    "year": "2021",
    "quality": "",
    "duration": "56 min",
    "description": "Ambientada en un mundo de fantasía donde la magia existe, pero solo unos pocos pueden",
    "director": "Rafe Judkins",
    "genres": [
      "Drama",
      "Sci-Fi & Fantasy"
    ],
    "actors": [
      "Ceara Coveney",
      "Daniel Henney",
      "Dónal Finn",
      "Josha Stradowski",
      "Madeleine Madden",
      "Marcus Rutherford",
      "Rosamund Pike",
      "Zoë Robins"
    ]
  },
  {
    "title": "Invasión",
    "link": "https://cinetux.top/serie/invasion/",
    "image": "https://cinetux.top/wp-content/themes/toroflix%202/public/img/cnt/noimga.svg",
    "year": "2021",
    "quality": "",
    "duration": "",
    "description": "La llegada de una especie alienígena a la Tierra pone en peligro a toda la",
    "director": "David Weil",
    "genres": [
      "Drama",
      "Sci-Fi & Fantasy"
    ],
    "actors": [
      "Azhy Robertson",
      "Billy Barratt",
      "Enver Gjokaj",
      "Golshifteh Farahani",
      "India Brown",
      "Naian González Norvind",
      "Nedra Marie Taylor",
      "Paddy Holland",
      "Shamier Anderson",
      "Shioli Kutsuna",
      "Tara Moayedi"
    ]
  },
  {
    "title": "Yo soy Groot",
    "link": "https://cinetux.top/serie/yo-soy-groot/",
    "image": "https://cinetux.top/wp-content/themes/toroflix%202/public/img/cnt/noimga.svg",
    "year": "2022",
    "quality": "",
    "duration": "5 min",
    "description": "Una serie de cortometrajes con Groot junto a varios personajes inusuales. Es infantil y molesta",
    "director": "Kirsten Lepore",
    "genres": [
      "Animación",
      "Comedia",
      "Familia",
      "Sci-Fi & Fantasy"
    ],
    "actors": [
      "Vin Diesel"
    ]
  },
  {
    "title": "ONE PIECE",
    "link": "https://cinetux.top/serie/one-piece/",
    "image": "https://cinetux.top/wp-content/themes/toroflix%202/public/img/cnt/noimga.svg",
    "year": "2023",
    "quality": "",
    "duration": "",
    "description": "El joven pirata Monkey D. Luffy y su variopinta tripulación emprenden un viaje épico en",
    "director": "Matt Owens",
    "genres": [
      "Action & Adventure",
      "Sci-Fi & Fantasy"
    ],
    "actors": [
      "Aidan Scott",
      "Emily Rudd",
      "Iñaki Godoy",
      "Jacob Gibson",
      "Jeff Ward",
      "Mackenyu",
      "Morgan Davies",
      "Taz Skylar",
      "Vincent Regan"
    ]
  },
  {
    "title": "Respira",
    "link": "https://cinetux.top/temporada/respira-1/",
    "image": "https://cinetux.top/wp-content/themes/toroflix%202/public/img/cnt/noimga.svg",
    "year": "",
    "quality": "1 - Episodios",
    "duration": "",
    "description": "",
    "director": "",
    "genres": [],
    "actors": []
  },
  {
    "title": "El Señor de los Anillos: Los anillos de poder",
    "link": "https://cinetux.top/temporada/el-senor-de-los-anillos-los-anillos-de-poder-2/",
    "image": "https://cinetux.top/wp-content/themes/toroflix%202/public/img/cnt/noimga.svg",
    "year": "",
    "quality": "3 - Episodios",
    "duration": "",
    "description": "",
    "director": "",
    "genres": [],
    "actors": []
  },
  {
    "title": "El Señor de los Anillos: Los anillos de poder",
    "link": "https://cinetux.top/temporada/el-senor-de-los-anillos-los-anillos-de-poder-0/",
    "image": "https://cinetux.top/wp-content/themes/toroflix%202/public/img/cnt/noimga.svg",
    "year": "",
    "quality": "0 - Episodios",
    "duration": "",
    "description": "",
    "director": "",
    "genres": [],
    "actors": []
  },
  {
    "title": "Solo asesinatos en el edificio",
    "link": "https://cinetux.top/temporada/solo-asesinatos-en-el-edificio-4/",
    "image": "https://cinetux.top/wp-content/themes/toroflix%202/public/img/cnt/noimga.svg",
    "year": "",
    "quality": "1 - Episodios",
    "duration": "",
    "description": "",
    "director": "",
    "genres": [],
    "actors": []
  },
  {
    "title": "Solo asesinatos en el edificio",
    "link": "https://cinetux.top/temporada/solo-asesinatos-en-el-edificio-3/",
    "image": "https://cinetux.top/wp-content/themes/toroflix%202/public/img/cnt/noimga.svg",
    "year": "",
    "quality": "0 - Episodios",
    "duration": "",
    "description": "",
    "director": "",
    "genres": [],
    "actors": []
  },
  {
    "title": "Solo asesinatos en el edificio",
    "link": "https://cinetux.top/temporada/solo-asesinatos-en-el-edificio-2/",
    "image": "https://cinetux.top/wp-content/themes/toroflix%202/public/img/cnt/noimga.svg",
    "year": "",
    "quality": "0 - Episodios",
    "duration": "",
    "description": "",
    "director": "",
    "genres": [],
    "actors": []
  },
  {
    "title": "Solo asesinatos en el edificio",
    "link": "https://cinetux.top/temporada/solo-asesinatos-en-el-edificio-1/",
    "image": "https://cinetux.top/wp-content/themes/toroflix%202/public/img/cnt/noimga.svg",
    "year": "",
    "quality": "0 - Episodios",
    "duration": "",
    "description": "",
    "director": "",
    "genres": [],
    "actors": []
  },
  {
    "title": "Tor",
    "link": "https://cinetux.top/temporada/tor-1/",
    "image": "https://cinetux.top/wp-content/themes/toroflix%202/public/img/cnt/noimga.svg",
    "year": "",
    "quality": "8 - Episodios",
    "duration": "",
    "description": "",
    "director": "",
    "genres": [],
    "actors": []
  },
  {
    "title": "Tor",
    "link": "https://cinetux.top/temporada/tor-0/",
    "image": "https://cinetux.top/wp-content/themes/toroflix%202/public/img/cnt/noimga.svg",
    "year": "",
    "quality": "0 - Episodios",
    "duration": "",
    "description": "",
    "director": "",
    "genres": [],
    "actors": []
  },
  {
    "title": "Los héroes del tiempo",
    "link": "https://cinetux.top/temporada/los-heroes-del-tiempo-1/",
    "image": "https://cinetux.top/wp-content/themes/toroflix%202/public/img/cnt/noimga.svg",
    "year": "",
    "quality": "10 - Episodios",
    "duration": "",
    "description": "",
    "director": "",
    "genres": [],
    "actors": []
  },
  {
    "title": "The Serpent Queen",
    "link": "https://cinetux.top/temporada/the-serpent-queen-2/",
    "image": "https://cinetux.top/wp-content/themes/toroflix%202/public/img/cnt/noimga.svg",
    "year": "",
    "quality": "5 - Episodios",
    "duration": "",
    "description": "",
    "director": "",
    "genres": [],
    "actors": []
  },
  {
    "title": "The Umbrella Academy",
    "link": "https://cinetux.top/temporada/the-umbrella-academy-4/",
    "image": "https://cinetux.top/wp-content/themes/toroflix%202/public/img/cnt/noimga.svg",
    "year": "",
    "quality": "6 - Episodios",
    "duration": "",
    "description": "",
    "director": "",
    "genres": [],
    "actors": []
  },
  {
    "title": "Respira",
    "link": "https://cinetux.top/capitulo/respira-1x1/",
    "year": "",
    "quality": "30-08-2024",
    "duration": "",
    "description": "",
    "director": "",
    "genres": [],
    "actors": []
  },
  {
    "title": "El Señor de los Anillos: Los anillos de poder",
    "link": "https://cinetux.top/capitulo/el-senor-de-los-anillos-los-anillos-de-poder-2x3/",
    "year": "",
    "quality": "29-08-2024",
    "duration": "",
    "description": "",
    "director": "",
    "genres": [],
    "actors": []
  },
  {
    "title": "El Señor de los Anillos: Los anillos de poder",
    "link": "https://cinetux.top/capitulo/el-senor-de-los-anillos-los-anillos-de-poder-2x2/",
    "year": "",
    "quality": "29-08-2024",
    "duration": "",
    "description": "",
    "director": "",
    "genres": [],
    "actors": []
  },
  {
    "title": "El Señor de los Anillos: Los anillos de poder",
    "link": "https://cinetux.top/capitulo/el-senor-de-los-anillos-los-anillos-de-poder-2x1/",
    "year": "",
    "quality": "29-08-2024",
    "duration": "",
    "description": "",
    "director": "",
    "genres": [],
    "actors": []
  },
  {
    "title": "Solo asesinatos en el edificio",
    "link": "https://cinetux.top/capitulo/solo-asesinatos-en-el-edificio-4x1/",
    "year": "",
    "quality": "27-08-2024",
    "duration": "",
    "description": "",
    "director": "",
    "genres": [],
    "actors": []
  },
  {
    "title": "Tor",
    "link": "https://cinetux.top/capitulo/tor-1x8/",
    "year": "",
    "quality": "17-06-2024",
    "duration": "",
    "description": "",
    "director": "",
    "genres": [],
    "actors": []
  },
  {
    "title": "Tor",
    "link": "https://cinetux.top/capitulo/tor-1x7/",
    "year": "",
    "quality": "10-06-2024",
    "duration": "",
    "description": "",
    "director": "",
    "genres": [],
    "actors": []
  },
  {
    "title": "Tor",
    "link": "https://cinetux.top/capitulo/tor-1x6/",
    "year": "",
    "quality": "03-06-2024",
    "duration": "",
    "description": "",
    "director": "",
    "genres": [],
    "actors": []
  },
  {
    "title": "Tor",
    "link": "https://cinetux.top/capitulo/tor-1x5/",
    "year": "",
    "quality": "27-05-2024",
    "duration": "",
    "description": "",
    "director": "",
    "genres": [],
    "actors": []
  },
  {
    "title": "Tor",
    "link": "https://cinetux.top/capitulo/tor-1x4/",
    "year": "",
    "quality": "20-05-2024",
    "duration": "",
    "description": "",
    "director": "",
    "genres": [],
    "actors": []
  },
  {
    "title": "Tor",
    "link": "https://cinetux.top/capitulo/tor-1x3/",
    "year": "",
    "quality": "13-05-2024",
    "duration": "",
    "description": "",
    "director": "",
    "genres": [],
    "actors": []
  },
  {
    "title": "Tor",
    "link": "https://cinetux.top/capitulo/tor-1x2/",
    "year": "",
    "quality": "06-05-2024",
    "duration": "",
    "description": "",
    "director": "",
    "genres": [],
    "actors": []
  }
]